{"eu":{"name":"Shatter.2184","rank":87,"oldRank":38,"rating":1663,"seasonsPlayed":[{"id":"B8823ECB-6E70-4D6F-BFC9-45768FA3C6B2","name":"PvP League Season Eight","rank":119,"rating":1770},{"id":"1BDC2ECA-5907-4D0D-9258-6B01EE3B7924","name":"PvP League 3v3 Season Three","rank":37,"rating":1661},{"id":"793D2076-A6F4-4D83-893F-18385D96A1E9","name":"PvP League Season Twenty-Six","rank":52,"rating":1699},{"id":"166B9DDC-DFF9-4828-B8D6-BC6441A98209","name":"PvP League 2v2 Season Five","rank":112,"rating":1566},{"id":"0626CBEF-32FC-444E-AE0A-52DE464A12D9","name":"PvP League Season Thirty-One","rank":115,"rating":1617}],"oldSeasonsPlayed":[{"id":"D1777261-555B-4B72-A27E-BDC96EC393D5","name":"PvP League Season Three","rank":38,"rating":6}],"scores":[{"id":"E6487336-4B5B-4BFA-9CFA-9FF232CAEF85","value":6},{"value":567},{"value":410}],"oldRating":6},"na":{"name":"Shatter.2184","rank":87,"oldRank":38,"rating":1663,"seasonsPlayed":[{"id":"B8823ECB-6E70-4D6F-BFC9-45768FA3C6B2","name":"PvP League Season Eight","rank":119,"rating":1770},{"id":"1BDC2ECA-5907-4D0D-9258-6B01EE3B7924","name":"PvP League 3v3 Season Three","rank":37,"rating":1661},{"id":"793D2076-A6F4-4D83-893F-18385D96A1E9","name":"PvP League Season Twenty-Six","rank":52,"rating":1699},{"id":"166B9DDC-DFF9-4828-B8D6-BC6441A98209","name":"PvP League 2v2 Season Five","rank":112,"rating":1566},{"id":"0626CBEF-32FC-444E-AE0A-52DE464A12D9","name":"PvP League Season Thirty-One","rank":115,"rating":1617}],"oldSeasonsPlayed":[{"id":"D1777261-555B-4B72-A27E-BDC96EC393D5","name":"PvP League Season Three","rank":38,"rating":6}],"scores":[{"id":"E6487336-4B5B-4BFA-9CFA-9FF232CAEF85","value":6},{"value":567},{"value":410}],"oldRating":6}}